selenium_supporter/__init__.py
selenium_supporter/drivers.py
selenium_supporter/utils.py
selenium_supporter-0.0.22.dist-info/METADATA
selenium_supporter-0.0.22.dist-info/WHEEL
selenium_supporter-0.0.22.dist-info/top_level.txt
selenium_supporter-0.0.22.dist-info/RECORD
