Metadata-Version: 2.1
Name: selenium-supporter
Version: 0.0.22
Summary: Selenium supporter
Home-page: https://github.com/automatethem/selenium-supporter
Author: Sang Ki Kwon
Author-email: automatethem@gmail.com
License: MIT
Requires-Dist: selenium ==4.3.0
Requires-Dist: webdriver-manager ==4.0.1
Requires-Dist: python-supporter
Requires-Dist: pyautogui
